vending_machine_def.v
// Macro constants (prefix k & CamelCase)
`define kTotalBits 32

`define kItemBits 8
`define kNumItems 4

`define kCoinBits 8
`define kNumCoins 3
`define kReturnCoins 10

`define kWaitTime 10

vending_machine.v
// `include "vending_machine_def.v"

// Macro constants (prefix k & CamelCase)
`define kTotalBits 32

`define kItemBits 8
`define kNumItems 4

`define kCoinBits 8
`define kNumCoins 3
`define kReturnCoins 10

`define kWaitTime 10


module vending_machine (

	clk,							// Clock signal
	reset_n,						// Reset signal (active-low)

	i_input_coin,				// coin is inserted.
	i_select_item,				// item is selected.
	i_trigger_return,			// change-return is triggered

	o_available_item,			// Sign of the item availability
	o_output_item,			   // Sign of the item withdrawal
	o_return_coin,			   // Sign of the coin return
	o_current_total
);

	// Ports Declaration
	input clk;
	input reset_n;

	input [`kNumCoins-1:0] i_input_coin;
	input [`kNumItems-1:0] i_select_item;
	input i_trigger_return;

	output [`kNumItems-1:0] o_available_item;
	output [`kNumItems-1:0] o_output_item;
	output [`kReturnCoins-1:0] o_return_coin;
	output [`kTotalBits-1:0] o_current_total;

	// Net constant values (prefix kk & CamelCase)
	wire [31:0] kkItemPrice [`kNumItems-1:0];	// Price of each item
	wire [31:0] kkCoinValue [`kNumCoins-1:0];	// Value of each coin
	assign kkItemPrice[0] = 400;
	assign kkItemPrice[1] = 500;
	assign kkItemPrice[2] = 1000;
	assign kkItemPrice[3] = 2000;
	assign kkCoinValue[0] = 100;
	assign kkCoinValue[1] = 500;
	assign kkCoinValue[2] = 1000;

	// Internal states. You may add your own reg variables.
	reg [`kTotalBits-1:0] current_total;
	reg [`kItemBits-1:0] num_items [`kNumItems-1:0]; //use if needed
	reg [`kCoinBits-1:0] num_coins [`kNumCoins-1:0]; //use if needed
	reg [1:0] state; // current state
	reg [1:0] nstate; // next state
	reg [`kNumItems-1:0] o_available_item_reg; // reg of o_available_item output variable for combinational circuit
	reg [`kNumItems-1:0] o_output_item_reg; // reg of o_output_item output variable for combinational circuit
	reg [`kReturnCoins-1:0] o_return_coin_reg; // reg of o_return_coin output variable for combinational circuit
	reg [`kTotalBits-1:0] o_current_total_reg; // reg of o_current_total output variable for combinational circuit
	
	// Combinational circuit for the next states
	always @(i_input_coin or i_select_item or i_trigger_return) begin // when any input changes
        if(i_input_coin) begin // if coin is input, then next state go to 01
            nstate = 2'b01;
        end
        else if(i_select_item) begin // if item is selected then next state go to 10
            nstate = 2'b10;
        end
        else if(i_trigger_return) begin // if return trigger is on, then next state go to 11
            nstate = 2'b11;
        end
	end

	// Combinational circuit for the output
	always @(posedge clk or state) begin // when posedge of clk or there is state change
	  
	   case (state)
	   	2'b00 : begin // 00 state is reset state
			o_current_total_reg = 0;
			o_output_item_reg = 4'b0000;
			o_return_coin_reg = 4'b0000;
			o_available_item_reg = 4'b0000;
		end
		2'b01 : begin // 01 state is input coin state updating o_current_total output variable
			o_current_total_reg = i_input_coin[0] * kkCoinValue[0] + i_input_coin[1] * kkCoinValue[1] + i_input_coin[2] * kkCoinValue[2] + o_current_total;
			// update current total coin amount by accumulating input coins
			o_output_item_reg = 4'b0000; // no output item
			o_return_coin_reg = 4'b0000; // no return coin
			o_available_item_reg = {(o_current_total_reg >= kkItemPrice[3]), (o_current_total_reg >= kkItemPrice[2]), (o_current_total_reg >= kkItemPrice[1]), (o_current_total_reg >= kkItemPrice[0])};
			// update available item according to current coin
		end
		2'b10 : begin // 10 state is select item state updating o_available_item ouput variable according to current coin amount
			o_return_coin_reg = 4'b0000; // no return coin
			o_output_item_reg = {(o_available_item[3] & i_select_item[3]), (o_available_item[2] & i_select_item[2]), (o_available_item[1] & i_select_item[1]), (o_available_item[0] & i_select_item[0])};
			// output item considering availble item and selected item
			if(o_output_item_reg[0]) begin
				o_current_total_reg = o_current_total - kkItemPrice[0]; // update current total coin amount after outputting selected item
			end
			else if(o_output_item_reg[1]) begin
				o_current_total_reg = o_current_total - kkItemPrice[1];
			end
			else if(o_output_item_reg[2]) begin
				o_current_total_reg = o_current_total - kkItemPrice[2];
			end
			else if(o_output_item_reg[3]) begin
				o_current_total_reg = o_current_total - kkItemPrice[3];
			end
		    o_available_item_reg = {(o_current_total_reg >= kkItemPrice[3]), (o_current_total_reg >= kkItemPrice[2]), (o_current_total_reg >= kkItemPrice[1]), (o_current_total_reg >= kkItemPrice[0])};
			// update available item after outputting selected item
		end
		2'b11 : begin // 11 state is return coin state updating o_return_coin output variable according to current coin amount
		    o_return_coin_reg=0;
			o_output_item_reg = 4'b0000; // No output item
			o_return_coin_reg = o_current_total / kkCoinValue[2]; // quotient of current total coin amount devided by kkCoinValue[x] is # of coins
			o_current_total_reg = o_current_total_reg % kkCoinValue[2]; // remainder of current total coin amount devided by kkCoinValue[x] is the new current total coin amount
		   	o_return_coin_reg = o_return_coin_reg + (o_current_total_reg / kkCoinValue[1]);
			o_current_total_reg = o_current_total_reg % kkCoinValue[1];
		   	o_return_coin_reg = o_return_coin_reg + (o_current_total_reg / kkCoinValue[0]);
			o_current_total_reg = o_current_total_reg % kkCoinValue[0];
			o_available_item_reg = 4'b0000; // No available item
			nstate = 2'b00; // next state go to reset state because all of output variables are zero after return change coins
		end
	   endcase
	end

	// Sequential circuit to reset or update the states
	
	assign o_available_item = o_available_item_reg; // assign reg variables to output variables
	assign o_output_item = o_output_item_reg;		// reg variables are computed in combinational circuit
	assign o_return_coin = o_return_coin_reg;
	assign o_current_total = o_current_total_reg;
	
	always @(posedge clk) begin
		if (!reset_n) begin
			// TODO: reset all states.
			state <= 2'b00; // reset state
		end
		else begin
			// TODO: update all states.
			state <= nstate; // putting next state on current state
		end
	end
endmodule

tests/vending_machine_TB.v
`timescale 100ps / 100ps

`include "vending_machine_def.v"

module vending_machine_tb;


//Internal signal declaration
reg clk;
reg reset_n;
reg [2:0]i_input_coin;
reg [3:0]i_select_item;
reg i_trigger_return;
wire [3:0]o_available_item;
wire [3:0]o_output_item;
wire [9:0]o_return_coin;
wire [31:0]o_current_total;

integer Passed;
integer Failed;

// Unit Under Test port map
	vending_machine UUT (
		.clk(clk),
		.reset_n(reset_n),
		.i_input_coin(i_input_coin),
		.i_select_item(i_select_item),
		.i_trigger_return(i_trigger_return),
		.o_available_item(o_available_item),
		.o_output_item(o_output_item),
		.o_return_coin(o_return_coin),
		.o_current_total(o_current_total));

// clock signal
initial clk <= 0;
always #50 clk <= ~clk; // a clock cycle: # 100, a half cycle: # 50

initial begin
	// Reset the device
	reset_n = 1;
	#50 reset_n = 0;
	#100 reset_n = 1;

	// Initialize input signals
	i_input_coin[0] = 0;
	i_input_coin[1] = 0;
	i_input_coin[2] = 0;
	i_select_item[0] = 0;
	i_select_item[1] = 0;
	i_select_item[2] = 0;
	i_select_item[3] = 0;
	i_trigger_return = 0;


	# 150; // Wait until the output signals are stable.
	Insert100Coin();
	Insert100Coin();
	Insert100Coin();
	Insert100Coin();
	Insert100Coin(); // 500

	Insert500Coin();
	Insert500Coin(); // 1500

	Insert1000Coin();
	Insert1000Coin();
	Insert1000Coin();
	Insert1000Coin(); // 5500

	Select1stItem();
	Select1stItem(); // 4700

	Select2ndItem();
	Select2ndItem(); // 3700

	Select3rdItem(); // 2700

	Select4thItem(); // 700

	Insert100Coin();
	Insert100Coin();
	Insert100Coin();
	Insert500Coin();
	Insert500Coin();
	Insert500Coin();
	Insert1000Coin();
	Insert1000Coin();
	Insert1000Coin(); //5500

	TriggerReturn(); // 0
    TriggerReturn();
    Insert1000Coin();
    TriggerReturn();

	#10000 $finish(0);
end

initial begin
    Passed = 0;
    Failed = 0;
    #600 //600
    general_check(4'b0000, 4'b0000, 100);
    #200 //800
    general_check(4'b0000, 4'b0000, 200);
    #200 //1000
    general_check(4'b0000, 4'b0000, 300);
    #200 //1200
    general_check(4'b0001, 4'b0000, 400);
    #200 //1400
    general_check(4'b0011, 4'b0000, 500);
    #200 //1600
    general_check(4'b0111, 4'b0000, 1000);
    #200 //1800
    general_check(4'b0111, 4'b0000, 1500);
    #200 //2000
    general_check(4'b1111, 4'b0000, 2500);
    #200 //2200
    general_check(4'b1111, 4'b0000, 3500);
    #200 //2400
    general_check(4'b1111, 4'b0000, 4500);
    #200 //2600
    general_check(4'b1111, 4'b0000, 5500);
    #100 //2700
    general_check(4'b1111, 4'b0001, 5100);
    #200 //2900
    general_check(4'b1111, 4'b0001, 4700);
    #200 //3100
    general_check(4'b1111, 4'b0010, 4200);
    #200 //3300
    general_check(4'b1111, 4'b0010, 3700);
    #200 //3500
    general_check(4'b1111, 4'b0100, 2700);
    #200 //3700
    general_check(4'b0011, 4'b1000, 700);
    #200 //3900
    general_check(4'b0011, 4'b0000, 800);
    #200 //4100
    general_check(4'b0011, 4'b0000, 900);
    #200 //4300
    general_check(4'b0111, 4'b0000, 1000);
    #200 //4500
    general_check(4'b0111, 4'b0000, 1500);
    #200 //4700
    general_check(4'b1111, 4'b0000, 2000);
    #200 //4900
    general_check(4'b1111, 4'b0000, 2500);
    #200 //5100
    general_check(4'b1111, 4'b0000, 3500);
    #200 //5300
    general_check(4'b1111, 4'b0000, 4500);
    #200 //5500
    general_check(4'b1111, 4'b0000, 5500);
    #200 //5700
    general_check(4'b0000, 4'b0000, 0);
    return_check(6);
    #200 //5900
    general_check(4'b0000, 4'b0000, 0);

    $display("Passed = %0d, Failed = %0d", Passed, Failed);
end
task general_check;

    input [`kNumItems-1:0] available_item;
    input [`kNumItems-1:0] output_item;
    input [`kTotalBits-1:0] current_total;
    begin
        if(available_item == o_available_item && output_item == o_output_item && current_total == o_current_total) begin
            Passed = Passed + 1;
            $display("PASSED");
        end
        else begin
            Failed = Failed + 1;
            $display("FAILED at %0d", $time, "ns");
            $display("Correct ans=> o_available_item: 4'b%b, o_output_item: 4'b%b, o_current_total: %0d", available_item, output_item, current_total);
        end
    end
endtask
task return_check;

    input [`kNumCoins-1:0] return_coin;
    begin
        if(return_coin == o_return_coin) begin
            Passed = Passed + 1;
            $display("PASSED");
        end
        else begin
            Failed = Failed + 1;
            $display("FAILED at %0d", $time, "ns");
            $display("Correct ans=> o_return_coin: %0d", return_coin);
        end
    end
endtask

// User's Action
task Insert100Coin;
begin
	# 100 i_input_coin[0] = 1;
	# 100 i_input_coin[0] = 0;	// After one cycle, deactivate the signal
end
endtask

task Insert500Coin;
begin
	# 100 i_input_coin[1] = 1;
	# 100 i_input_coin[1] = 0;	// After one cycle, deactivate the signal
end
endtask

task Insert1000Coin;
begin
	# 100 i_input_coin[2] = 1;
	# 100 i_input_coin[2] = 0;	// After one cycle, deactivate the signal
end
endtask

task Select1stItem;
begin
	# 100 i_select_item[0] = 1;
	# 100 i_select_item[0] = 0;	// After one cycle, deactivate the signal
end
endtask

task Select2ndItem;
begin
	# 100 i_select_item[1] = 1;
	# 100 i_select_item[1] = 0;	// After one cycle, deactivate the signal
end
endtask

task Select3rdItem;
begin
	# 100 i_select_item[2] = 1;
	# 100 i_select_item[2] = 0;	// After one cycle, deactivate the signal
end
endtask

task Select4thItem;
begin
	# 100 i_select_item[3] = 1;
	# 100 i_select_item[3] = 0; 	// After one cycle, deactivate the signal
end
endtask

task TriggerReturn;
begin
	# 100 i_trigger_return = 1;
    # 100 i_trigger_return = 0;
end
endtask

endmodule

waveforms/vending_machine_TB.vcd
$date
	Sun May 12 00:10:17 2024
$end
$version
	Icarus Verilog
$end
$timescale
	100ps
$end
$scope module vending_machine_tb $end
$var wire 10 ! o_return_coin [9:0] $end
$var wire 4 " o_output_item [3:0] $end
$var wire 32 # o_current_total [31:0] $end
$var wire 4 $ o_available_item [3:0] $end
$var reg 1 % clk $end
$var reg 3 & i_input_coin [2:0] $end
$var reg 4 ' i_select_item [3:0] $end
$var reg 1 ( i_trigger_return $end
$var reg 1 ) reset_n $end
$var integer 32 * Failed [31:0] $end
$var integer 32 + Passed [31:0] $end
$scope module UUT $end
$var wire 1 % clk $end
$var wire 3 , i_input_coin [2:0] $end
$var wire 4 - i_select_item [3:0] $end
$var wire 1 ( i_trigger_return $end
$var wire 4 . o_available_item [3:0] $end
$var wire 32 / o_current_total [31:0] $end
$var wire 4 0 o_output_item [3:0] $end
$var wire 10 1 o_return_coin [9:0] $end
$var wire 1 ) reset_n $end
$var reg 2 2 nstate [1:0] $end
$var reg 4 3 o_available_item_reg [3:0] $end
$var reg 32 4 o_current_total_reg [31:0] $end
$var reg 4 5 o_output_item_reg [3:0] $end
$var reg 10 6 o_return_coin_reg [9:0] $end
$var reg 2 7 state [1:0] $end
$upscope $end
$scope task Insert1000Coin $end
$upscope $end
$scope task Insert100Coin $end
$upscope $end
$scope task Insert500Coin $end
$upscope $end
$scope task Select1stItem $end
$upscope $end
$scope task Select2ndItem $end
$upscope $end
$scope task Select3rdItem $end
$upscope $end
$scope task Select4thItem $end
$upscope $end
$scope task TriggerReturn $end
$upscope $end
$scope task general_check $end
$var reg 4 8 available_item [3:0] $end
$var reg 32 9 current_total [31:0] $end
$var reg 4 : output_item [3:0] $end
$upscope $end
$scope task return_check $end
$var reg 3 ; return_coin [2:0] $end
$upscope $end
$upscope $end
$enddefinitions $end
#0
$dumpvars
bx ;
bx :
bx 9
bx 8
bx 7
bx 6
bx 5
bx 4
bx 3
bx 2
bx 1
bx 0
bx /
bx .
bx -
bx ,
b0 +
b0 *
1)
x(
bx '
bx &
0%
bx $
bx #
bx "
bx !
$end
#50
b0 $
b0 .
b0 3
b0 !
b0 1
b0 6
b0 "
b0 0
b0 5
b0 #
b0 /
b0 4
b0 7
1%
0)
#100
0%
#150
bx 7
1%
0(
b0 '
b0 -
b0 &
b0 ,
1)
#200
0%
#250
1%
#300
0%
#350
1%
#400
0%
b1 2
b1 &
b1 ,
#450
b1100100 #
b1100100 /
b1100100 4
b1 7
1%
#500
0%
b0 &
b0 ,
#550
1%
#600
0%
b1 &
b1 ,
b1 +
b1100100 9
b0 :
b0 8
#650
b11001000 #
b11001000 /
b11001000 4
1%
#700
0%
b0 &
b0 ,
#750
1%
#800
0%
b1 &
b1 ,
b10 +
b11001000 9
#850
b100101100 #
b100101100 /
b100101100 4
1%
#900
0%
b0 &
b0 ,
#950
1%
#1000
0%
b1 &
b1 ,
b11 +
b100101100 9
#1050
b1 $
b1 .
b1 3
b110010000 #
b110010000 /
b110010000 4
1%
#1100
0%
b0 &
b0 ,
#1150
1%
#1200
0%
b1 &
b1 ,
b100 +
b110010000 9
b1 8
#1250
b11 $
b11 .
b11 3
b111110100 #
b111110100 /
b111110100 4
1%
#1300
0%
b0 &
b0 ,
#1350
1%
#1400
0%
b10 &
b10 ,
b101 +
b111110100 9
b11 8
#1450
b111 $
b111 .
b111 3
b1111101000 #
b1111101000 /
b1111101000 4
1%
#1500
0%
b0 &
b0 ,
#1550
1%
#1600
0%
b10 &
b10 ,
b110 +
b1111101000 9
b111 8
#1650
b10111011100 #
b10111011100 /
b10111011100 4
1%
#1700
0%
b0 &
b0 ,
#1750
1%
#1800
0%
b100 &
b100 ,
b111 +
b10111011100 9
#1850
b1111 $
b1111 .
b1111 3
b100111000100 #
b100111000100 /
b100111000100 4
1%
#1900
0%
b0 &
b0 ,
#1950
1%
#2000
0%
b100 &
b100 ,
b1000 +
b100111000100 9
b1111 8
#2050
b110110101100 #
b110110101100 /
b110110101100 4
1%
#2100
0%
b0 &
b0 ,
#2150
1%
#2200
0%
b100 &
b100 ,
b1001 +
b110110101100 9
#2250
b1000110010100 #
b1000110010100 /
b1000110010100 4
1%
#2300
0%
b0 &
b0 ,
#2350
1%
#2400
0%
b100 &
b100 ,
b1010 +
b1000110010100 9
#2450
b1010101111100 #
b1010101111100 /
b1010101111100 4
1%
#2500
0%
b0 &
b0 ,
#2550
1%
#2600
0%
b10 2
b1 '
b1 -
b1011 +
b1010101111100 9
#2650
b1001111101100 #
b1001111101100 /
b1001111101100 4
b1 "
b1 0
b1 5
b10 7
1%
#2700
0%
b0 '
b0 -
b1100 +
b1001111101100 9
b1 :
#2750
b0 "
b0 0
b0 5
1%
#2800
0%
b1 '
b1 -
#2850
b1001001011100 #
b1001001011100 /
b1001001011100 4
b1 "
b1 0
b1 5
1%
#2900
0%
b0 '
b0 -
b1101 +
b1001001011100 9
#2950
b0 "
b0 0
b0 5
1%
#3000
0%
b10 '
b10 -
#3050
b1000001101000 #
b1000001101000 /
b1000001101000 4
b10 "
b10 0
b10 5
1%
#3100
0%
b0 '
b0 -
b1110 +
b1000001101000 9
b10 :
#3150
b0 "
b0 0
b0 5
1%
#3200
0%
b10 '
b10 -
#3250
b111001110100 #
b111001110100 /
b111001110100 4
b10 "
b10 0
b10 5
1%
#3300
0%
b0 '
b0 -
b1111 +
b111001110100 9
#3350
b0 "
b0 0
b0 5
1%
#3400
0%
b100 '
b100 -
#3450
b101010001100 #
b101010001100 /
b101010001100 4
b100 "
b100 0
b100 5
1%
#3500
0%
b0 '
b0 -
b10000 +
b101010001100 9
b100 :
#3550
b0 "
b0 0
b0 5
1%
#3600
0%
b1000 '
b1000 -
#3650
b11 $
b11 .
b11 3
b1010111100 #
b1010111100 /
b1010111100 4
b1000 "
b1000 0
b1000 5
1%
#3700
0%
b0 '
b0 -
b10001 +
b1010111100 9
b1000 :
b11 8
#3750
b0 "
b0 0
b0 5
1%
#3800
0%
b1 2
b1 &
b1 ,
#3850
b1100100000 #
b1100100000 /
b1100100000 4
b1 7
1%
#3900
0%
b0 &
b0 ,
b10010 +
b1100100000 9
b0 :
#3950
1%
#4000
0%
b1 &
b1 ,
#4050
b1110000100 #
b1110000100 /
b1110000100 4
1%
#4100
0%
b0 &
b0 ,
b10011 +
b1110000100 9
#4150
1%
#4200
0%
b1 &
b1 ,
#4250
b111 $
b111 .
b111 3
b1111101000 #
b1111101000 /
b1111101000 4
1%
#4300
0%
b0 &
b0 ,
b10100 +
b1111101000 9
b111 8
#4350
1%
#4400
0%
b10 &
b10 ,
#4450
b10111011100 #
b10111011100 /
b10111011100 4
1%
#4500
0%
b0 &
b0 ,
b10101 +
b10111011100 9
#4550
1%
#4600
0%
b10 &
b10 ,
#4650
b1111 $
b1111 .
b1111 3
b11111010000 #
b11111010000 /
b11111010000 4
1%
#4700
0%
b0 &
b0 ,
b10110 +
b11111010000 9
b1111 8
#4750
1%
#4800
0%
b10 &
b10 ,
#4850
b100111000100 #
b100111000100 /
b100111000100 4
1%
#4900
0%
b0 &
b0 ,
b10111 +
b100111000100 9
#4950
1%
#5000
0%
b100 &
b100 ,
#5050
b110110101100 #
b110110101100 /
b110110101100 4
1%
#5100
0%
b0 &
b0 ,
b11000 +
b110110101100 9
#5150
1%
#5200
0%
b100 &
b100 ,
#5250
b1000110010100 #
b1000110010100 /
b1000110010100 4
1%
#5300
0%
b0 &
b0 ,
b11001 +
b1000110010100 9
#5350
1%
#5400
0%
b100 &
b100 ,
#5450
b1010101111100 #
b1010101111100 /
b1010101111100 4
1%
#5500
0%
b0 &
b0 ,
b11010 +
b1010101111100 9
#5550
1%
#5600
0%
b11 2
1(
#5650
b0 2
b0 $
b0 .
b0 3
b0 #
b0 /
b0 4
b110 !
b110 1
b110 6
b11 7
1%
#5700
0%
0(
b110 ;
b11100 +
b0 9
b0 8
#5750
b0 7
b0 !
b0 1
b0 6
1%
#5800
0%
b11 2
1(
#5850
b0 2
b11 7
1%
#5900
0%
0(
b11101 +
#5950
b0 7
1%
#6000
0%
b1 2
b100 &
b100 ,
#6050
b111 $
b111 .
b111 3
b1111101000 #
b1111101000 /
b1111101000 4
b1 7
1%
#6100
0%
b0 &
b0 ,
#6150
1%
#6200
0%
b11 2
1(
#6250
b0 2
b0 $
b0 .
b0 3
b0 #
b0 /
b0 4
b1 !
b1 1
b1 6
b11 7
1%
#6300
0%
0(
#6350
b0 7
b0 !
b0 1
b0 6
1%
